tapyoca/__init__.py
tapyoca/agglutination/__init__.py
tapyoca/agglutination/data_acquisition.py
tapyoca/agglutination/partitions.py
tapyoca/agglutination/py_names.py
tapyoca/covid/__init__.py
tapyoca/covid/covid_bar_chart_race.py
tapyoca/darpa/__init__.py
tapyoca/darpa/darpa.py
tapyoca/demonyms/__init__.py
tapyoca/demonyms/data_acquisition.py
tapyoca/indexing_podcasts/__init__.py
tapyoca/indexing_podcasts/prep.py
tapyoca/parquet_deformations/__init__.py
tapyoca/parquet_deformations/parquet_deformations.py
tapyoca/parquet_deformations/py_fonts.py
tapyoca/phonecode/__init__.py
tapyoca/phonecode/demo_phonecode.py
tapyoca/phonecode/phonecode.py
tapyoca/phonecode/quickstart_guide.py
tapyoca/phonecode/test_phonecode.py
tapyoca/phoneming/__init__.py
tapyoca/phoneming/explore.py
tapyoca-0.0.7.dist-info/licenses/LICENSE
tapyoca-0.0.7.dist-info/METADATA
tapyoca-0.0.7.dist-info/WHEEL
tapyoca-0.0.7.dist-info/top_level.txt
tapyoca-0.0.7.dist-info/RECORD
