Metadata-Version: 2.4
Name: tapyoca
Version: 0.0.7
Summary: A medley of things that got coded because there was an itch to do so
Home-page: https://github.com/thorwhalen/tapyoca
Author: thorwhalen
License: Apache Software License
Keywords: documentation,packaging,publishing
Platform: any
License-File: LICENSE
Provides-Extra: testing
Dynamic: author
Dynamic: description
Dynamic: description-content-type
Dynamic: home-page
Dynamic: keywords
Dynamic: license
Dynamic: license-file
Dynamic: platform
Dynamic: summary
